MANIFEST.in
README.md
setup.py
DataAccess/ConnectionConfigurationClient.py
DataAccess/FileSystemIO.py
DataAccess/LinkedinClient.py
DataAccess/MongoConnectionClient.py
DataAccess/MysqlConnectionClient.py
DataAccess/Neo4jConnectionClient.py
DataAccess/RabbitMQConsumer.py
DataAccess/RabbitMQProducer.py
DataAccess/SparkConnectionClient.py
DataAccess/__init__.py
DataMining/PatriciaNode.py
DataMining/PatriciaTrie.py
DataMining/TextAnalytics.py
DataMining/__init__.py
LocationClients/LocationClient.py
LocationClients/__init__.py
Utils/Constants.py
Utils/ImageComparison.py
Utils/JEntityHelper.py
Utils/PandasHelper.py
Utils/PickleAnalyzer.py
Utils/ProfileHelper.py
Utils/StringUtils.py
Utils/TextFunctions.py
Utils/__init__.py
jobutils.egg-info/PKG-INFO
jobutils.egg-info/SOURCES.txt
jobutils.egg-info/dependency_links.txt
jobutils.egg-info/requires.txt
jobutils.egg-info/top_level.txt