Metadata-Version: 1.0
Name: jobutils
Version: 0.1.4
Summary: Helpers for data related activities
Home-page: UNKNOWN
Author: joberate
Author-email: UNKNOWN
License: UNKNOWN
Platform: UNKNOWN
